{
  "report_type": "Lighthouse Performance Report - Combined Desktop & Mobile",
  "pages": [
    {
      "page": "Design Construction",
      "url": "https://ogs.ny.gov/design-construction",
      "desktop": {
        "link": "ogs.ny.gov-design-construction-desktop.html",
        "title": "Lighthouse Report - Desktop",
        "performance_score": 55,
        "metrics": {
          "first_contentful_paint": "5.8 s",
          "largest_contentful_paint": "21.9 s",
          "total_blocking_time": "0 ms",
          "cumulative_layout_shift": "0.048",
          "speed_index": "5.8 s"
        }
      },
      "mobile": {
        "link": "ogs.ny.gov-design-construction-mobile.html",
        "title": "Lighthouse Report - Mobile",
        "performance_score": 60,
        "metrics": {
          "first_contentful_paint": "5.9 s",
          "largest_contentful_paint": "19.9 s",
          "total_blocking_time": "60 ms",
          "cumulative_layout_shift": "0",
          "speed_index": "5.9 s"
        }
      },
      "score_ranges": {
        "poor": "0-49",
        "needs_improvement": "50-89",
        "good": "90-100"
      }
    },
    {
      "page": "Home",
      "url": "https://ogs.ny.gov/",
      "desktop": {
        "link": "ogs.ny.gov-desktop.html",
        "title": "Lighthouse Report - Desktop",
        "performance_score": 55,
        "metrics": {
          "first_contentful_paint": "9.4 s",
          "largest_contentful_paint": "21.6 s",
          "total_blocking_time": "0 ms",
          "cumulative_layout_shift": "0.048",
          "speed_index": "9.4 s"
        }
      },
      "mobile": {
        "link": "ogs.ny.gov-mobile.html",
        "title": "Lighthouse Report - Mobile",
        "performance_score": 56,
        "metrics": {
          "first_contentful_paint": "9.7 s",
          "largest_contentful_paint": "21.9 s",
          "total_blocking_time": "20 ms",
          "cumulative_layout_shift": "0",
          "speed_index": "9.7 s"
        }
      },
      "score_ranges": {
        "poor": "0-49",
        "needs_improvement": "50-89",
        "good": "90-100"
      }
    },
    {
      "page": "Centralized Contracts List",
      "url": "https://ogs.ny.gov/procurement/ogs-centralized-contracts-list",
      "desktop": {
        "link": "ogs.ny.gov-centralized-contracts-list-desktop.html",
        "title": "Lighthouse Report - Desktop",
        "performance_score": 55,
        "metrics": {
          "first_contentful_paint": "6.1 s",
          "largest_contentful_paint": "16.4 s",
          "total_blocking_time": "0 ms",
          "cumulative_layout_shift": "0.048",
          "speed_index": "6.1 s"
        }
      },
      "mobile": {
        "link": "ogs.ny.gov-centralized-contracts-list-mobile.html",
        "title": "Lighthouse Report - Mobile",
        "performance_score": 59,
        "metrics": {
          "first_contentful_paint": "6.1 s",
          "largest_contentful_paint": "15.4 s",
          "total_blocking_time": "120 ms",
          "cumulative_layout_shift": "0.001",
          "speed_index": "6.1 s"
        }
      },
      "score_ranges": {
        "poor": "0-49",
        "needs_improvement": "50-89",
        "good": "90-100"
      }
    },
    {
      "page": "Parking",
      "url": "https://ogs.ny.gov/parking",
      "desktop": {
        "link": "ogs.ny.gov-parking-desktop.html",
        "title": "Lighthouse Report - Desktop",
        "performance_score": 55,
        "metrics": {
          "first_contentful_paint": "5.8 s",
          "largest_contentful_paint": "21.0 s",
          "total_blocking_time": "0 ms",
          "cumulative_layout_shift": "0.054",
          "speed_index": "6.5 s"
        }
      },
      "mobile": {
        "link": "ogs.ny.gov-parking-mobile.html",
        "title": "Lighthouse Report - Mobile",
        "performance_score": 60,
        "metrics": {
          "first_contentful_paint": "5.8 s",
          "largest_contentful_paint": "19.2 s",
          "total_blocking_time": "50 ms",
          "cumulative_layout_shift": "0.001",
          "speed_index": "5.8 s"
        }
      },
      "score_ranges": {
        "poor": "0-49",
        "needs_improvement": "50-89",
        "good": "90-100"
      }
    },
    {
      "page": "Procurement",
      "url": "https://ogs.ny.gov/procurement",
      "desktop": {
        "link": "ogs.ny.gov-procurement-desktop.html",
        "title": "Lighthouse Report - Desktop",
        "performance_score": 55,
        "metrics": {
          "first_contentful_paint": "6.0 s",
          "largest_contentful_paint": "16.0 s",
          "total_blocking_time": "0 ms",
          "cumulative_layout_shift": "0.048",
          "speed_index": "6.0 s"
        }
      },
      "mobile": {
        "link": "ogs.ny.gov-procurement-mobile.html",
        "title": "Lighthouse Report - Mobile",
        "performance_score": 60,
        "metrics": {
          "first_contentful_paint": "5.7 s",
          "largest_contentful_paint": "17.2 s",
          "total_blocking_time": "110 ms",
          "cumulative_layout_shift": "0",
          "speed_index": "5.7 s"
        }
      },
      "score_ranges": {
        "poor": "0-49",
        "needs_improvement": "50-89",
        "good": "90-100"
      }
    }
  ]
}